myosuite_init.py
myosuite/__init__.py
myosuite/version.py
myosuite/agents/README.md
myosuite/agents/config_mujoco.yaml
myosuite/agents/hydra_mjrl_launcher.py
myosuite/agents/hydra_sb3_launcher.py
myosuite/agents/in_callbacks.py
myosuite/agents/mjrl_job_script.py
myosuite/agents/requirements_train.txt
myosuite/agents/sb3_job_script.py
myosuite/agents/torchrl_job_script.py
myosuite/agents/train_myosuite.sh
myosuite/agents/SAR_pretrained/locomotion/ica.pkl
myosuite/agents/SAR_pretrained/locomotion/normalizer.pkl
myosuite/agents/SAR_pretrained/locomotion/pca.pkl
myosuite/agents/SAR_pretrained/manipulation/ica.pkl
myosuite/agents/SAR_pretrained/manipulation/normalizer.pkl
myosuite/agents/SAR_pretrained/manipulation/pca.pkl
myosuite/agents/baseline_Reflex/ReflexCtrInterface.py
myosuite/agents/baseline_Reflex/reflexCtr.py
myosuite/agents/baselines_DEPRL/myoLegWalk.json
myosuite/agents/baselines_DEPRL/myoLegWalk_20230514/myoLeg/config.yaml
myosuite/agents/baselines_DEPRL/myoLegWalk_20230514/myoLeg/log.csv
myosuite/agents/baselines_DEPRL/myoLegWalk_20230514/myoLeg/checkpoints/read_for_checkpoint.txt
myosuite/agents/baslines_NPG/MyoSuite-NPG-Baseline.pdf
"myosuite/agents/baslines_NPG/motorFingerPoseFixed-v0/2022-02-26_21-16-27/18_env=motorFingerPoseFixed-v0,seed=1/job_config.yaml"
"myosuite/agents/baslines_NPG/motorFingerPoseFixed-v0/2022-02-26_21-16-27/18_env=motorFingerPoseFixed-v0,seed=1/results.txt"
"myosuite/agents/baslines_NPG/motorFingerPoseFixed-v0/2022-02-26_21-16-27/18_env=motorFingerPoseFixed-v0,seed=1/iterations/best_policy.pickle"
"myosuite/agents/baslines_NPG/motorFingerPoseFixed-v0/2022-02-26_21-16-27/18_env=motorFingerPoseFixed-v0,seed=1/logs/log.csv"
"myosuite/agents/baslines_NPG/motorFingerPoseFixed-v0/2022-02-26_21-16-27/18_env=motorFingerPoseFixed-v0,seed=1/logs/stoc_pol_mean.png"
"myosuite/agents/baslines_NPG/motorFingerPoseFixed-v0/2022-02-26_21-16-27/19_env=motorFingerPoseFixed-v0,seed=2/job_config.yaml"
MyoSuite-2.8.4.dist-info/LICENSE
MyoSuite-2.8.4.dist-info/METADATA
MyoSuite-2.8.4.dist-info/WHEEL
MyoSuite-2.8.4.dist-info/entry_points.txt
MyoSuite-2.8.4.dist-info/top_level.txt
MyoSuite-2.8.4.dist-info/RECORD
