Metadata-Version: 2.1
Name: MyoSuite
Version: 2.8.4
Summary: Musculoskeletal environments simulated in MuJoCo
Home-page: https://sites.google.com/view/myosuite
Author: MyoSuite Authors - Vikash Kumar (Meta AI), Vittorio Caggiano (Meta AI), Huawei Wang (University of Twente), Guillaume Durandau (University of Twente), Massimo Sartori (University of Twente)
Author-email: vikashplus@gmail.com
License: Apache 2.0
Platform: UNKNOWN
Classifier: Programming Language :: Python :: 3.8
Classifier: License :: OSI Approved :: Apache Software License
Classifier: Topic :: Scientific/Engineering :: Artificial Intelligence 
Classifier: Operating System :: OS Independent
Requires-Python: >=3.8
License-File: LICENSE
Requires-Dist: click
Requires-Dist: sk-video
Requires-Dist: gymnasium==0.29.1
Requires-Dist: termcolor
Requires-Dist: flatten-dict
Requires-Dist: h5py
Requires-Dist: numpy
Requires-Dist: mujoco==3.1.2
Requires-Dist: dm-control==1.0.16
Requires-Dist: Pillow
Requires-Dist: pink-noise-rl
Requires-Dist: packaging
Requires-Dist: gitpython
